mcp_server/README.md
mcp_server/__init__.py
mcp_server/application.py
mcp_server/server.py
mcp_server/config/__init__.py
mcp_server/config/config.py
mcp_server/consts/__init__.py
mcp_server/consts/consts.py
mcp_server/core/__init__.py
mcp_server/core/cdn/__init__.py
mcp_server/core/cdn/cdn.py
mcp_server/core/cdn/tools.py
mcp_server/core/media_processing/__init__.py
mcp_server/core/media_processing/processing.py
mcp_server/core/media_processing/tools.py
mcp_server/core/media_processing/utils.py
mcp_server/core/storage/__init__.py
mcp_server/core/storage/resource.py
mcp_server/core/storage/storage.py
mcp_server/core/storage/tools.py
mcp_server/core/version/__init__.py
mcp_server/core/version/tools.py
mcp_server/core/version/version.py
mcp_server/resource/__init__.py
mcp_server/resource/resource.py
mcp_server/tools/__init__.py
mcp_server/tools/tools.py
mseep_qiniu_mcp_server-1.2.6.dist-info/METADATA
mseep_qiniu_mcp_server-1.2.6.dist-info/WHEEL
mseep_qiniu_mcp_server-1.2.6.dist-info/entry_points.txt
mseep_qiniu_mcp_server-1.2.6.dist-info/licenses/LICENSE
mseep_qiniu_mcp_server-1.2.6.dist-info/RECORD
